Workbook

Sheet  RAW DATA
A1: RAW DATA
A2: METRIC | B2: MCL 2021 | C2: MCL 2022 | D2: MCL 2023 | E2: WIL 2021 | F2: WIL 2022 | G2: WIL 2023 | H2: MER 2021 | I2: MER 2022 | J2: MER 2023 | K2: AMR 2021 | L2: AMR 2022 | M2: AMR 2023
A3: Turnover | B3: 213017 | C3: 327870 | D3: 431048 | E3: 96396 | F3: 142835 | G3: 127043 | H3: 383302 | I3: 474570 | J3: 546478 | K3: 150438 | L3: 188728 | M3: 244652
A4: Operating P/L | B4: 15920 | C4: 22949 | D4: 35101 | E4: 10131 | F4: 14561 | G4: 84233 | H4: 71938 | I4: 113640 | J4: 113836 | K4: 39579 | L4: 52714 | M4: 21679
A5: Net P/L | B5: 7419 | C5: 7412 | D5: 26117 | E5: 11940 | F5: 17896 | G5: 83892 | H5: 68806 | I5: 89733 | J5: 83825 | K5: 43332 | L5: 52915 | M5: 29705
A6: Total Assets | B6: 278515 | C6: 329987 | D6: 415518 | E6: 136897 | F6: 165116 | G6: 206128 | H6: 304247 | I6: 356583 | J6: 416876 | K6: 70362 | L6: 246158 | M6: 332761
A7: Cash | B7: 35250 | C7: 17630 | D7: 17232 | E7: 35160 | F7: 23281 | G7: 39025 | H7: 4171 | I7: 38012 | J7: 33186 | K7: 125000 | L7: 69774 | M7: 78773
A8: Total Liabilities | B8: 186167 | C8: 207770 | D8: 246136 | E8: 37539 | F8: 50436 | G8: 67095 | H8: 164224 | I8: 174507 | J8: 200053 | K8: 49848 | L8: 278544 | M8: 394852
A9: Employees | B9: 867 | C9: 1025 | D9: 1218 | E9: 720 | F9: 785 | G9: 1029 | H9: 1004 | I9: 1114 | J9: 1289 | K9: 457 | L9: 449 | M9: 369

Sheet RATIO ANALYSIS WITH FORMULAS
A1: RATIO ANALYSIS WITH FORMULAS
A2: RATIO NAME | B2: MCL 2021 | C2: MCL 2022 | D2: MCL 2023 | E2: WIL 2021 | F2: WIL 2022 | G2: WIL 2023 | H2: MER 2021 | I2: MER 2022 | J2: MER 2023 | K2: AMR 2021 | L2: AMR 2022 | M2: AMR 2023
A3: EBIT Margin (%) | B3: =' RAW DATA'!B4/' RAW DATA'!B3*100 -> 7.4735819 | C3: =' RAW DATA'!C4/' RAW DATA'!C3*100 -> 6.9994205 | D3: =' RAW DATA'!D4/' RAW DATA'!D3*100 -> 8.1431766 | E3: =' RAW DATA'!E4/' RAW DATA'!E3*100 -> 10.509772 | F3: =' RAW DATA'!F4/' RAW DATA'!F3*100 -> 10.19428 | G3: =' RAW DATA'!G4/' RAW DATA'!G3*100 -> 66.302748 | H3: =' RAW DATA'!H4/' RAW DATA'!H3*100 -> 18.767969 | I3: =' RAW DATA'!I4/' RAW DATA'!I3*100 -> 23.945888 | ... M3: =' RAW DATA'!M4/' RAW DATA'!M3*100 -> 8.8611579
A4: Net Profit Margin (%) | B4: =' RAW DATA'!B5/' RAW DATA'!B3*100 -> 3.4828206 | C4: =' RAW DATA'!C5/' RAW DATA'!C3*100 -> 2.2606521 | D4: =' RAW DATA'!D5/' RAW DATA'!D3*100 -> 6.058954 | E4: =' RAW DATA'!E5/' RAW DATA'!E3*100 -> 12.386406 | F4: =' RAW DATA'!F5/' RAW DATA'!F3*100 -> 12.529142 | G4: =' RAW DATA'!G5/' RAW DATA'!G3*100 -> 66.034335 | H4: =' RAW DATA'!H5/' RAW DATA'!H3*100 -> 17.950859 | I4: =' RAW DATA'!I5/' RAW DATA'!I3*100 -> 18.908275 | ... M4: =' RAW DATA'!M5/' RAW DATA'!M3*100 -> 12.141736
A5: Return on Assets (%) | B5: =' RAW DATA'!B5/' RAW DATA'!B6*100 -> 2.6637704 | C5: =' RAW DATA'!C5/' RAW DATA'!C6*100 -> 2.2461491 | D5: =' RAW DATA'!D5/' RAW DATA'!D6*100 -> 6.2854076 | E5: =' RAW DATA'!E5/' RAW DATA'!E6*100 -> 8.7218858 | F5: =' RAW DATA'!F5/' RAW DATA'!F6*100 -> 10.838441 | G5: =' RAW DATA'!G5/' RAW DATA'!G6*100 -> 40.698983 | H5: =' RAW DATA'!H5/' RAW DATA'!H6*100 -> 22.615178 | I5: =' RAW DATA'!I5/' RAW DATA'!I6*100 -> 25.164688 | ... M5: =' RAW DATA'!M5/' RAW DATA'!M6*100 -> 8.9268274
A6: Asset Turnover | B6: =' RAW DATA'!B3/' RAW DATA'!B6 -> 0.76483134 | C6: =' RAW DATA'!C3/' RAW DATA'!C6 -> 0.9935846 | D6: =' RAW DATA'!D3/' RAW DATA'!D6 -> 1.037375 | E6: =' RAW DATA'!E3/' RAW DATA'!E6 -> 0.70414984 | F6: =' RAW DATA'!F3/' RAW DATA'!F6 -> 0.8650585 | G6: =' RAW DATA'!G3/' RAW DATA'!G6 -> 0.61633063 | H6: =' RAW DATA'!H3/' RAW DATA'!H6 -> 1.2598382 | I6: =' RAW DATA'!I3/' RAW DATA'!I6 -> 1.3308823 | ... M6: =' RAW DATA'!M3/' RAW DATA'!M6 -> 0.73521837
A7: Revenue per Employee | B7: =' RAW DATA'!B3/' RAW DATA'!B9 -> 245.69435 | C7: =' RAW DATA'!C3/' RAW DATA'!C9 -> 319.87317 | D7: =' RAW DATA'!D3/' RAW DATA'!D9 -> 353.89819 | E7: =' RAW DATA'!E3/' RAW DATA'!E9 -> 133.88333 | F7: =' RAW DATA'!F3/' RAW DATA'!F9 -> 181.95541 | G7: =' RAW DATA'!G3/' RAW DATA'!G9 -> 123.46259 | H7: =' RAW DATA'!H3/' RAW DATA'!H9 -> 381.7749 | I7: =' RAW DATA'!I3/' RAW DATA'!I9 -> 426.00539 | ... M7: =' RAW DATA'!M3/' RAW DATA'!M9 -> 663.01355
A8: Net Equity | B8: =' RAW DATA'!B6-' RAW DATA'!B8 -> 92348 | C8: =' RAW DATA'!C6-' RAW DATA'!C8 -> 122217 | D8: =' RAW DATA'!D6-' RAW DATA'!D8 -> 169382 | E8: =' RAW DATA'!E6-' RAW DATA'!E8 -> 99358 | F8: =' RAW DATA'!F6-' RAW DATA'!F8 -> 114680 | G8: =' RAW DATA'!G6-' RAW DATA'!G8 -> 139033 | H8: =' RAW DATA'!H6-' RAW DATA'!H8 -> 140023 | I8: =' RAW DATA'!I6-' RAW DATA'!I8 -> 182076 | ... M8: =' RAW DATA'!M6-' RAW DATA'!M8 -> -62091
A9: Debt-to-Equity | B9: =' RAW DATA'!B6/B8 -> 3.0159289 | C9: =' RAW DATA'!C6/C8 -> 2.700009 | D9: =' RAW DATA'!D6/D8 -> 2.4531414 | E9: =' RAW DATA'!E6/E8 -> 1.3778156 | F9: =' RAW DATA'!F6/F8 -> 1.4397977 | G9: =' RAW DATA'!G6/G8 -> 1.4825833 | H9: =' RAW DATA'!H6/H8 -> 2.1728359 | I9: =' RAW DATA'!I6/I8 -> 1.9584294 | ... M9: =' RAW DATA'!M6/M8 -> -5.3592469
A10: Return on Equity (%) | B10: =' RAW DATA'!B5/B8*100 -> 8.0337419 | C10: =' RAW DATA'!C5/C8*100 -> 6.0646228 | D10: =' RAW DATA'!D5/D8*100 -> 15.418994 | E10: =' RAW DATA'!E5/E8*100 -> 12.01715 | F10: =' RAW DATA'!F5/F8*100 -> 15.605162 | G10: =' RAW DATA'!G5/G8*100 -> 60.339632 | H10: =' RAW DATA'!H5/H8*100 -> 49.13907 | I10: =' RAW DATA'!I5/I8*100 -> 49.283266 | ... M10: =' RAW DATA'!M5/M8*100 -> -47.841072
A11: Revenue Growth (%) | C11: =(' RAW DATA'!C3-' RAW DATA'!B3)/' RAW DATA'!B3*100 -> 53.917293 | D11: =(' RAW DATA'!D3-' RAW DATA'!C3)/' RAW DATA'!C3*100 -> 31.46918 | F11: =(' RAW DATA'!F3-' RAW DATA'!E3)/' RAW DATA'!E3*100 -> 48.175235 | G11: =(' RAW DATA'!G3-' RAW DATA'!F3)/' RAW DATA'!F3*100 -> -11.056114 | I11: =(' RAW DATA'!I3-' RAW DATA'!H3)/' RAW DATA'!H3*100 -> 23.81099 | J11: =(' RAW DATA'!J3-' RAW DATA'!I3)/' RAW DATA'!I3*100 -> 15.152243 | L11: =(' RAW DATA'!L3-' RAW DATA'!K3)/' RAW DATA'!K3*100 -> 25.452346 | M11: =(' RAW DATA'!M3-' RAW DATA'!L3)/' RAW DATA'!L3*100 -> 29.632063

Sheet VALUATION
A1: VALUATION BENCHMARKS
A3: Metric | B3: Value
A4: Average F1 Team EV/Revenue Multiple | B4: 6
A5: Average Sports Franchise EV/Revenue | B5: 4.5
A6: F1 Entry Fee (New Team) | B6: 200
A9: TEAM VALUATIONS (Using 6x Revenue Multiple)
A11: Team | B11: 2023 Revenue (£000) | C11: Estimated EV (£M)
A12: McLaren | B12: =' RAW DATA'!D3 -> 431048 | C12: =B12*6/1000 -> 2586.288
A13: Williams | B13: =' RAW DATA'!G3 -> 127043 | C13: =B13*6/1000 -> 762.258
A14: Mercedes | B14: =' RAW DATA'!J3 -> 546478 | C14: =B14*6/1000 -> 3278.868
A15: Aston Martin | B15: =' RAW DATA'!M3 -> 244652 | C15: =B15*6/1000 -> 1467.912
A18: EBITDA VALUATION (Using 15x EBITDA Multiple)
A20: Team | B20: 2023 Operating Profit (£000) | C20: Estimated EV (£M)
A21: McLaren | B21: =' RAW DATA'!D4 -> 35101 | C21: =B21*15/1000 -> 526.515
A22: Williams | B22: =' RAW DATA'!G4 -> 84233 | C22: =B22*15/1000 -> 1263.495
A23: Mercedes | B23: =' RAW DATA'!J4 -> 113836 | C23: =B23*15/1000 -> 1707.54
A24: Aston Martin | B24: =' RAW DATA'!M4 -> 21679 | C24: =B24*15/1000 -> 325.185
A27: SIMPLIFIED DCF - McLAREN EXAMPLE
A29: Year | B29: Revenue Projection (£000) | C29: EBIT (8% margin) | D29: Discount Factor (10% WACC) | E29: Present Value
A30: 2024E | B30: =' RAW DATA'!D3*15 -> 6465720 | C30: =B30*0.08 -> 517257.6 | D30: =1/(1.1^1) -> 0.90909091 | E30: =C30*D30 -> 470234.18
A31: 2025E | B31: =B30*1.12 -> 7241606.4 | C31: =B31*0.08 -> 579328.51 | D31: =1/(1.1^2) -> 0.82644628 | E31: =C31*D31 -> 478783.89
A32: 2026E | B32: =B31*1.1 -> 7965767 | C32: =B32*0.08 -> 637261.36 | D32: =1/(1.1^3) -> 0.7513148 | E32: =C32*D32 -> 478783.89
A33: 2027E | B33: =B32*1.08 -> 8603028.4 | C33: =B33*0.08 -> 688242.27 | D33: =1/(1.1^4) -> 0.68301346 | E33: =C33*D33 -> 470078.73
A34: 2028E | B34: =B33*1.05 -> 9033179.8 | C34: =B34*0.08 -> 722654.39 | D34: =1/(1.1^5) -> 0.62092132 | E34: =C34*D34 -> 448711.52
A36: Sum of PV Cash Flows | B36: =SUM(E30:E34)/1000 -> 2346.5922
A37: Terminal Value (10x EBIT) | B37: =C34*10/1000 -> 7226.5439
A38: PV of Terminal Value | B38: =B37*D34 -> 4487.1152
A40: ENTERPRISE VALUE (£000) | B40: =B36+B38 -> 6833.7074
A41: ENTERPRISE VALUE (£B) | B41: =B40/1000 -> 6.8337074

Sheet SUMMARY
A1: F1 TEAMS FINANCIAL ANALYSIS - KEY FINDINGS
A3: SECTION 1: REVENUE ANALYSIS
A5: Metric | B5: McLaren | C5: Williams | D5: Mercedes | E5: Aston Martin
A6: 2023 Revenue (£M) | B6: =' RAW DATA'!D3/1000 -> 431.048 | C6: =' RAW DATA'!G3/1000 -> 127.043 | D6: =' RAW DATA'!J3/1000 -> 546.478 | E6: =' RAW DATA'!M3/1000 -> 244.652
A7: 3-Year Revenue Growth | B7: =((' RAW DATA'!D3-' RAW DATA'!B3)/' RAW DATA'!B3)*100 -> 102.3538 | C7: =((' RAW DATA'!G3-' RAW DATA'!E3)/' RAW DATA'!E3)*100 -> 31.792813 | D7: =((' RAW DATA'!J3-' RAW DATA'!H3)/' RAW DATA'!H3)*100 -> 42.571132 | E7: =((' RAW DATA'!M3-' RAW DATA'!K3)/' RAW DATA'!K3)*100 -> 62.626464
A8: Ranking by Revenue | B8: 2 | C8: 4 | D8: 1 | E8: 3
A10: KEY INSIGHT: Mercedes leads revenue (£546M) but McLaren shows strongest 3-year growth. Williams smallest by revenue but improving.
A13: SECTION 2: PROFITABILITY ANALYSIS
A15: Metric | B15: McLaren | C15: Williams | D15: Mercedes | E15: Aston Martin
A16: 2023 EBIT Margin (%) | B16: ='RATIO ANALYSIS WITH FORMULAS'!D3 -> 8.1431766 | C16: ='RATIO ANALYSIS WITH FORMULAS'!G3 -> 66.302748 | D16: ='RATIO ANALYSIS WITH FORMULAS'!J3 -> 20.830848 | E16: ='RATIO ANALYSIS WITH FORMULAS'!M3 -> 8.8611579
A17: 2023 Net Profit (£M) | B17: =' RAW DATA'!D5/1000 -> 26.117 | C17: =' RAW DATA'!G5/1000 -> 83.892 | D17: =' RAW DATA'!J5/1000 -> 83.825 | E17: =' RAW DATA'!M5/1000 -> 29.705
A18: Return on Equity (%) | B18: ='RATIO ANALYSIS WITH FORMULAS'!D10 -> 15.418994 | C18: ='RATIO ANALYSIS WITH FORMULAS'!G10 -> 60.339632 | D18: ='RATIO ANALYSIS WITH FORMULAS'!J10 -> 38.660566 | E18: ='RATIO ANALYSIS WITH FORMULAS'!M10 -> -47.841072
A19: Ranking by EBIT Margin | B19: 4 | C19: 1 | D19: 2 | E19: 3
A21: KEY INSIGHT: Williams achieved exceptional 66% EBIT margin in 2023 (vs industry avg 8-10%), driven by cost cap compliance and operational efficiency. Mercedes maintains consistent profitability.
A24: SECTION 3: VALUATION SUMMARY
A26: Valuation Method | B26: McLaren | C26: Williams | D26: Mercedes | E26: Aston Martin
A27: Revenue Multiple (6x) £M | B27: =VALUATION!C12 -> 2586.288 | C27: =VALUATION!C13 -> 762.258 | D27: =VALUATION!C14 -> 3278.868 | E27: =VALUATION!C15 -> 1467.912
A28: EBITDA Multiple (15x) £M | B28: =VALUATION!C21 -> 526.515 | C28: =VALUATION!C22 -> 1263.495 | D28: =VALUATION!C23 -> 1707.54 | E28: =VALUATION!C24 -> 325.185
A29: DCF (McLaren only) £B | B29: =VALUATION!B41 -> 6.8337074
A31: Valuation Range | B31: £527M - £2,586M | C31: £762M - £1,264M | D31: £1,708M - £3,279M | E31: £325M - £1,468M
A33: KEY INSIGHT: Revenue-based valuations significantly exceed profitability-based estimates. EBITDA multiple provides more conservative, earnings-justified valuation. Williams shows inverse relationship: low revenue but high EBITDA valuation due to superior margins.
A36: SECTION 4: EFFICIENCY & PRODUCTIVITY
A38: Metric | B38: McLaren | C38: Williams | D38: Mercedes | E38: Aston Martin
A39: Revenue per Employee (£000) | B39: ='RATIO ANALYSIS WITH FORMULAS'!D7 -> 353.89819 | C39: ='RATIO ANALYSIS WITH FORMULAS'!G7 -> 123.46259 | D39: ='RATIO ANALYSIS WITH FORMULAS'!J7 -> 423.955 | E39: ='RATIO ANALYSIS WITH FORMULAS'!M7 -> 663.01355
A40: Employees (2023) | B40: =' RAW DATA'!D9 -> 1218 | C40: =' RAW DATA'!G9 -> 1029 | D40: =' RAW DATA'!J9 -> 1289 | E40: =' RAW DATA'!M9 -> 369
A41: Asset Turnover | B41: ='RATIO ANALYSIS WITH FORMULAS'!D6 -> 1.037375 | C41: ='RATIO ANALYSIS WITH FORMULAS'!G6 -> 0.61633063 | D41: ='RATIO ANALYSIS WITH FORMULAS'!J6 -> 1.3108886 | E41: ='RATIO ANALYSIS WITH FORMULAS'!M6 -> 0.73521837
A43: KEY INSIGHT: Mercedes achieves highest revenue per employee (£424k) reflecting scale efficiency. Aston Martin lowest productivity (£663k per employee) suggests operational inefficiencies.
A46: SECTION 5: FINANCIAL HEALTH
A48: Metric | B48: McLaren | C48: Williams | D48: Mercedes | E48: Aston Martin
A49: Debt-to-Equity Ratio | B49: ='RATIO ANALYSIS WITH FORMULAS'!D9 -> 2.4531414 | C49: ='RATIO ANALYSIS WITH FORMULAS'!G9 -> 1.4825833 | D49: ='RATIO ANALYSIS WITH FORMULAS'!J9 -> 1.9226558 | E49: ='RATIO ANALYSIS WITH FORMULAS'!M9 -> -5.3592469
A50: Cash Position (£M) | B50: =' RAW DATA'!D7/1000 -> 17.232 | C50: =' RAW DATA'!G7/1000 -> 39.025 | D50: =' RAW DATA'!J7/1000 -> 33.186 | E50: =' RAW DATA'!M7/1000 -> 78.773
A51: Net Equity (£M) | B51: ='RATIO ANALYSIS WITH FORMULAS'!D8/1000 -> 169.382 | C51: ='RATIO ANALYSIS WITH FORMULAS'!G8/1000 -> 139.033 | D51: ='RATIO ANALYSIS WITH FORMULAS'!J8/1000 -> 216.823 | E51: ='RATIO ANALYSIS WITH FORMULAS'!M8/1000 -> -62.091
A53: KEY INSIGHT: Williams maintains strongest balance sheet (low leverage, positive equity). Aston Martin highly leveraged, indicating aggressive growth investment or financial stress.
A56: TOP 3 INVESTMENT INSIGHTS
A58: 1. MERCEDES: Market leader by scale and consistency. £3.3B revenue-based valuation justified by dominant market position and stable profitability. Best positioned for sustained performance.
A60: 2. WILLIAMS: Turnaround story. Exceptional 2023 margins (66% EBIT) drive EBITDA valuation premium despite smallest revenue base. Strong balance sheet provides financial stability. Key risk: margin sustainability under competitive pressure.
A62: 3. McLAREN: Growth trajectory evident (102% revenue increase 2021-2023) but profitability lags. Revenue multiple (£2.6B) significantly exceeds EBITDA valuation (£527M), suggesting market overvaluation relative to earnings power. Requires margin improvement to justify premium valuation.
A65: BULL vs BEAR CASE SUMMARY
A67: BULL CASE: F1 commercial growth (Netflix effect, US expansion) lifts all teams. Cost cap creates competitive parity, increasing franchise value scarcity. Growing private equity interest validates premium multiples.
A69: BEAR CASE: Cost cap limits revenue reinvestment, constraining growth. Performance volatility impacts prize money (40-50% of revenue). High operational leverage makes teams vulnerable to competitive setbacks. Valuation multiples compressed if Liberty Media growth story falters.

Sheet TABLEAU EXPORT
A1: Team | B1: Year | C1: Revenue | D1: Operating_Profit | E1: Net_Profit | F1: Total_Assets | G1: Cash | H1: Employees | I1: EBIT_Margin | J1: Net_Margin | K1: ROE | L1: Asset_Turnover | M1: Revenue_per_Employee | N1: Debt_to_Equity | O1: Revenue Multiple Val | P1: EBITDA Multiple Val | Q1: DCF Val
A2: McLaren | B2: 2021 | C2: 213017 | D2: 15920 | E2: 7419 | F2: 278515 | G2: 35250 | H2: 867 | I2: 7.48 | J2: 3.48 | K2: 8.04 | L2: 0.76 | M2: 245.69 | N2: 2.02
A3: McLaren | B3: 2022 | C3: 327870 | D3: 22949 | E3: 7412 | F3: 329987 | G3: 17630 | H3: 1025 | I3: 7 | J3: 2.26 | K3: 6.06 | L3: 0.99 | M3: 319.88 | N3: 1.7
A4: McLaren | B4: 2023 | C4: 431048 | D4: 35101 | E4: 26117 | F4: 415518 | G4: 17232 | H4: 1218 | I4: 8.14 | J4: 6.06 | K4: 15.43 | L4: 1.04 | M4: 353.9 | N4: 1.45 | O4: 2586 | P4: 527 | Q4: 6834
A5: Williams | B5: 2021 | C5: 96396 | D5: 10131 | E5: 11940 | F5: 136897 | G5: 35160 | H5: 720 | I5: 10.51 | J5: 12.38 | K5: 12.01 | L5: 0.7 | M5: 133.88 | N5: 0.38
A6: Williams | B6: 2022 | C6: 142835 | D6: 14561 | E6: 17896 | F6: 165116 | G6: 23281 | H6: 785 | I6: 10.19 | J6: 12.53 | K6: 15.6 | L6: 0.87 | M6: 181.95 | N6: 0.44
A7: Williams | B7: 2023 | C7: 127043 | D7: 84233 | E7: 83892 | F7: 206128 | G7: 39025 | H7: 1029 | I7: 66.3 | J7: 66.02 | K7: 60.36 | L7: 0.62 | M7: 123.46 | N7: 0.48 | O7: 762 | P7: 1264
A8: Mercedes | B8: 2021 | C8: 383302 | D8: 71938 | E8: 68806 | F8: 304247 | G8: 4171 | H8: 1004 | I8: 18.77 | J8: 17.95 | K8: 49.14 | L8: 1.26 | M8: 381.77 | N8: 1.17
A9: Mercedes | B9: 2022 | C9: 474570 | D9: 113640 | E9: 89733 | F9: 356583 | G9: 38012 | H9: 1114 | I9: 23.95 | J9: 18.91 | K9: 49.26 | L9: 1.33 | M9: 426.05 | N9: 0.96
A10: Mercedes | B10: 2023 | C10: 546478 | D10: 113836 | E10: 83825 | F10: 416876 | G10: 33186 | H10: 1289 | I10: 20.83 | J10: 15.34 | K10: 38.69 | L10: 1.31 | M10: 423.95 | N10: 0.92 | O10: 3279 | P10: 1708
A11: Aston_Martin | B11: 2021 | C11: 150438 | D11: 39579 | E11: 43332 | F11: 70362 | G11: 125000 | H11: 457 | I11: 26.31 | J11: 28.8 | K11: 211.34 | L11: 2.14 | M11: 329.19 | N11: 2.42
A12: Aston_Martin | B12: 2022 | C12: 188728 | D12: 52714 | E12: 52915 | F12: 246158 | G12: 69774 | H12: 449 | I12: 27.93 | J12: 28.04 | K12: 15.65 | L12: 0.77 | M12: 420.33 | N12: -8.35
A13: Aston_Martin | B13: 2023 | C13: 244652 | D13: 21679 | E13: 29705 | F13: 332761 | G13: 78773 | H13: 369 | I13: 8.86 | J13: 12.14 | K13: -6.06 | L13: 0.74 | M13: 663.01 | N13: -8.09 | O13: 1468 | P13: 325
